meeko/__init__.py
meeko/atomtyper.py
meeko/bondtyper.py
meeko/chemtempgen.py
meeko/covalentbuilder.py
meeko/espalomatyper.py
meeko/export_flexres.py
meeko/flexibility.py
meeko/gridbox.py
meeko/hydrate.py
meeko/macrocycle.py
meeko/molecule_pdbqt.py
meeko/molsetup.py
meeko/openff_xml_parser.py
meeko/polymer.py
meeko/preparation.py
meeko/rdkit_mol_create.py
meeko/reactive.py
meeko/receptor_pdbqt.py
meeko/writer.py
meeko/analysis/__init__.py
meeko/analysis/fingerprint_interactions.py
meeko/analysis/interactions.py
meeko/cli/__init__.py
meeko/cli/mk_export.py
meeko/cli/mk_prepare_ligand.py
meeko/cli/mk_prepare_receptor.py
meeko/data/NAKB_templates.json
meeko/data/residue_chem_templates.json
meeko/tmp/compute_water_map.py
meeko/tmp/water_builder.py
meeko/tmp/water_map_builder.py
meeko/utils/__init__.py
meeko/utils/autodock4_atom_types_elements.py
meeko/utils/covalent_radius_table.py
meeko/utils/geomutils.py
meeko/utils/jsonutils.py
meeko/utils/pdbutils.py
meeko/utils/prodyutils.py
meeko/utils/rdkitutils.py
meeko/utils/utils.py
meeko/utils/van_der_waals_radius_table.py
meeko-0.6.0.dist-info/LICENSE
meeko-0.6.0.dist-info/METADATA
meeko-0.6.0.dist-info/WHEEL
meeko-0.6.0.dist-info/entry_points.txt
meeko-0.6.0.dist-info/top_level.txt
meeko-0.6.0.dist-info/RECORD
