Metadata-Version: 2.1
Name: meeko
Version: 0.6.0
Summary: Python package for preparing small molecule for docking
Home-page: https://github.com/ccsb-scripps/meeko
Author: Forli Lab
Author-email: forli@scripps.edu
License: LGPL-2.1
Keywords: molecular modeling,drug design,docking,autodock
Classifier: Environment :: Console
Classifier: Environment :: Other Environment
Classifier: Intended Audience :: Education
Classifier: Intended Audience :: Science/Research
Classifier: License :: OSI Approved :: GNU Lesser General Public License v2 or later (LGPLv2+)
Classifier: Natural Language :: English
Classifier: Operating System :: MacOS :: MacOS X
Classifier: Operating System :: OS Independent
Classifier: Operating System :: POSIX :: Linux
Classifier: Programming Language :: C++
Classifier: Programming Language :: Python
Classifier: Topic :: Scientific/Engineering :: Bio-Informatics
Classifier: Topic :: Scientific/Engineering :: Chemistry
Classifier: Topic :: Software Development :: Libraries
Requires-Python: >=3.9, <3.12
License-File: LICENSE
Requires-Dist: numpy>=1.18
Requires-Dist: rdkit
Requires-Dist: scipy
Requires-Dist: gemmi
